{"size":2,"cards":{"text":{"size":1,"mobile":"sim","desktop":"sim"},"banner":{"size":2,"type":"image","mobile":"sim","desktop":"sim","vertical":"end","srcMobile":"https://ozksgdmyrqcxcwhnbepg.supabase.co/storage/v1/object/public/assets/1285/480c52e7-d120-48cc-9d6f-1e6b32139663","sizeMobile":1,"srcDesktop":"https://ozksgdmyrqcxcwhnbepg.supabase.co/storage/v1/object/public/assets/1285/338af20d-ede4-4d1b-ac7d-6d2e997b5031","desalinhamento":true,"desalinhamentoAltura":"margin-top--100px"}},"ordem":"Card/Movie/Text","horizontal":"center","sizeMobile":1,"productCard":{"sort":"price:desc","count":2,"fuzzy":"automatic","query":"ipiranga","__resolveType":"deco-sites/std/loaders/vtex/intelligentSearch/productListingPage.ts","selectedFacets":[]},"borderRadius":{"mobile":"none","desktop":"none"},"__resolveType":"site/sections/BannerCardPosition.tsx","desalinhamento":"margin-top-100px"}