{"name":"teste brasileiro include","layout":{"__resolveType":"Layout Igor"},"sections":[{"title":"Fashion Store","canonical":"https://example.com","description":"Fashion by Deco","__resolveType":"deco-sites/std/sections/SEO.tsx"},{"images":[{"alt":"Feminino","action":{"href":"/feminino","label":"Conferir agora!","title":"Nova coleçāo","subTitle":"Blooming"},"mobile":"https://ozksgdmyrqcxcwhnbepg.supabase.co/storage/v1/object/public/assets/239/9a6288d3-c86a-4fcf-9109-0aa0a3ca0844","desktop":"https://ozksgdmyrqcxcwhnbepg.supabase.co/storage/v1/object/public/assets/239/d934fff6-02f5-4e0d-b459-f2af1f8ab8c5"},{"alt":"Feminino","action":{"href":"/feminino","label":"Conferir agora!","title":"Coleçāo outuno","subTitle":"Boost o seu SEO"},"mobile":"https://ozksgdmyrqcxcwhnbepg.supabase.co/storage/v1/object/public/assets/239/152717c9-b276-46dd-9556-871f20d71240","desktop":"https://ozksgdmyrqcxcwhnbepg.supabase.co/storage/v1/object/public/assets/239/d3e2bcab-a3f5-45dd-ae5b-6259418386d8"},{"alt":"Feminino","action":{"href":"/feminino","label":"Conferir agora!","title":"Ande como nunca!","subTitle":"Blooming"},"mobile":"https://ozksgdmyrqcxcwhnbepg.supabase.co/storage/v1/object/public/assets/239/18566873-00f6-40c0-9c00-653058aef59f","desktop":"https://ozksgdmyrqcxcwhnbepg.supabase.co/storage/v1/object/public/assets/239/29979ca1-4e1c-4ca5-bdaa-cc6f21e140ec"},{"alt":"vestidos","action":{"href":"/feminino","label":"Conferir agora!","title":"De um sol nesse verāo","subTitle":"SEO como nunca antes visto"},"mobile":"https://ozksgdmyrqcxcwhnbepg.supabase.co/storage/v1/object/public/assets/239/a6e75dbf-4fcb-4e44-9115-18cba7cf652b","desktop":"https://ozksgdmyrqcxcwhnbepg.supabase.co/storage/v1/object/public/assets/239/590dc37a-6cf4-47cf-80c8-29a2af432912"}],"preload":true,"interval":2,"__resolveType":"site/sections/Carousel.tsx"},{"title":"Mais Vendidos","products":{"count":9,"query":"camisa","__resolveType":"deco-sites/std/functions/vtexProductList.ts"},"__resolveType":"site/sections/ProductShelf.tsx"},{"title":"Categorias","highlights":[{"alt":"Mochilas","src":"https://ozksgdmyrqcxcwhnbepg.supabase.co/storage/v1/object/public/assets/239/152e3b3d-63ed-42b6-9363-29807c6c9ec6","href":"/feminino/jaquetas","label":"Mochilas"},{"alt":"Bolsas","src":"https://ozksgdmyrqcxcwhnbepg.supabase.co/storage/v1/object/public/assets/239/85857d6d-79e0-4257-afab-bfd283468738","href":"/feminino","label":"Bolsas"},{"alt":"Sapatos","src":"https://ozksgdmyrqcxcwhnbepg.supabase.co/storage/v1/object/public/assets/239/a6da6cf5-8872-4da3-a5ed-439b14bda5ba","href":"/138?map=productClusterIds","label":"Sapatos"},{"alt":"Jaquetas","src":"https://ozksgdmyrqcxcwhnbepg.supabase.co/storage/v1/object/public/assets/239/a5bd257f-b77e-4357-bc7f-334812dfcfef","href":"/139?map=productClusterIds","label":"Jaquetas"},{"alt":"Calças","src":"https://ozksgdmyrqcxcwhnbepg.supabase.co/storage/v1/object/public/assets/239/8583b029-9fd1-40e6-a6f8-c671b5898c4b","href":"/137?map=productClusterIds","label":"Calças"},{"alt":"Shorts","src":"https://ozksgdmyrqcxcwhnbepg.supabase.co/storage/v1/object/public/assets/239/1115570c-d626-43d9-a956-73be56078f78","href":"/137?map=productClusterIds","label":"Shorts"}],"__resolveType":"site/sections/Highlights.tsx"},{"features":[{"icon":"Truck","title":"Entrega em todo Brasil","description":"Consulte o prazo no fechamento."},{"icon":"Discount","title":"15% na primeira compra","description":"Aplicado direto na sacola."},{"icon":"Return","title":"Devolução grátis","description":"Faça login e preencha o forumário."},{"icon":"CreditCard","title":"Parcelamento em 12x","description":"Sem juros em todos os produtos"}],"__resolveType":"site/sections/Features.tsx"},{"phone":559552292960,"__resolveType":"site/sections/WhatsApp.tsx"},{"__resolveType":"site/sections/CookieConsent.tsx"}],"__resolveType":"$live/pages/LivePage.tsx"}